src/__init__.py
src/video_processor.py
src/xml_parser.py
CVAT_Video_Annotation_Processor-1.1.1.dist-info/LICENSE
CVAT_Video_Annotation_Processor-1.1.1.dist-info/METADATA
CVAT_Video_Annotation_Processor-1.1.1.dist-info/WHEEL
CVAT_Video_Annotation_Processor-1.1.1.dist-info/top_level.txt
CVAT_Video_Annotation_Processor-1.1.1.dist-info/RECORD
