Metadata-Version: 2.1
Name: CVAT-Video-Annotation-Processor
Version: 1.1.1
Summary: CVAT Video Annotation Processor is a Python package for processing videos with annotations generated by CVAT (Computer Vision Annotation Tool). It provides functions for parsing XML annotations, extracting ROIs (Regions of Interest) from videos, and saving the processed videos with labeled ROIs. This package is useful for computer vision and machine learning projects that require processing annotated videos for training or analysis
Author-email: kailash Hambarde <kailas.srt@gmail.com>
Project-URL: Homepage, https://github.com/kailashhambarde/CVAT_Video_Annotation_Processor.git
Project-URL: Issues, https://github.com/kailashhambarde/CVAT_Video_Annotation_Processor.git/issues
Project-URL: Project, https://github.com/kailashhambarde/CVAT_Video_Annotation_Processor.git
Classifier: Programming Language :: Python :: 3
Classifier: License :: OSI Approved :: MIT License
Classifier: Operating System :: OS Independent
Requires-Python: >=3.8
License-File: LICENSE
Requires-Dist: numpy
Requires-Dist: opencv-python
Requires-Dist: xmltodict
